poectrl/__init__.py
poectrl/api/__init__.py
poectrl/api/main.py
poectrl/api/managers/PoE.py
poectrl/api/resources/__init__.py
poectrl/api/resources/control.py
poectrl/api/resources/home.py
poectrl/api/schemas/__init__.py
poectrl/api/schemas/base.py
poectrl/api/schemas/request/__init__.py
poectrl/api/schemas/response/__init__.py
poectrl/api/schemas/response/poe.py
poectrl/api/settings.py
poectrl/base.py
poectrl/cliapp.py
poectrl/errors.py
poectrl/main.py
poectrl/profiles.py
poectrl/sshwrapper.py
poectrl-0.4.2.dist-info/METADATA
poectrl-0.4.2.dist-info/entry_points.txt
poectrl-0.4.2.dist-info/LICENSE.txt
poectrl-0.4.2.dist-info/WHEEL
poectrl-0.4.2.dist-info/RECORD
