Metadata-Version: 2.1
Name: poectrl
Version: 0.4.2
Summary: Control PoE status on select Ubiquiti switches
Home-page: https://github.com/seapagan/ts-8-pro-control
License: MIT
Author: Grant Ramsay
Author-email: seapagan@gmail.com
Requires-Python: >=3.7.2,<4.0
Classifier: Development Status :: 4 - Beta
Classifier: Environment :: Console
Classifier: Intended Audience :: Developers
Classifier: Intended Audience :: End Users/Desktop
Classifier: Intended Audience :: System Administrators
Classifier: License :: OSI Approved :: MIT License
Classifier: Operating System :: OS Independent
Classifier: Programming Language :: Python :: 3
Classifier: Programming Language :: Python :: 3.8
Classifier: Programming Language :: Python :: 3.9
Classifier: Programming Language :: Python :: 3.10
Classifier: Programming Language :: Python :: 3.11
Classifier: Programming Language :: Python :: 3
Classifier: Programming Language :: Python :: 3.10
Classifier: Programming Language :: Python :: 3.7
Classifier: Programming Language :: Python :: 3.8
Classifier: Programming Language :: Python :: 3.9
Requires-Dist: fastapi[all] (>=0.88,<0.96)
Requires-Dist: paramiko (>=2.12,<4.0)
Requires-Dist: typer[all] (>=0.7.0,<0.8.0)
Project-URL: Bug Tracker, https://github.com/seapagan/openapi-readme/issues
Project-URL: Pull Requests, https://github.com/seapagan/openapi-readme/pulls
Project-URL: Repository, https://github.com/seapagan/ts-8-pro-control
